{
  "timestamp": "2025-09-18T16:16:55.597Z",
  "totalComponents": 62,
  "rootComponents": [
    "index",
    "index",
    "index",
    "PanelContext",
    "index",
    "PanelTitle",
    "Typography",
    "index",
    "index",
    "index",
    "index",
    "StudioHall",
    "ModalManager",
    "index",
    "index",
    "index",
    "index",
    "index",
    "index",
    "index",
    "index",
    "index",
    "index",
    "ActionList",
    "ImageCarousel",
    "MindLog"
  ],
  "components": [
    {
      "name": "Button",
      "path": "common/Button/Button",
      "renders": [
        "StyledButton"
      ],
      "children": []
    },
    {
      "name": "index",
      "path": "common/Button/index",
      "renders": [],
      "children": []
    },
    {
      "name": "IconButton",
      "path": "common/IconButton/IconButton",
      "renders": [
        "ButtonContainer",
        "IconWrapper",
        "Label"
      ],
      "children": []
    },
    {
      "name": "MarkdownEditor",
      "path": "common/MarkdownEditor/MarkdownEditor",
      "renders": [
        "EditorContainer",
        "EditorContent",
        "Textarea",
        "MarkdownPreview"
      ],
      "children": [
        "MarkdownPreview"
      ]
    },
    {
      "name": "MarkdownPreview",
      "path": "common/MarkdownEditor/MarkdownPreview/MarkdownPreview",
      "renders": [
        "PreviewContainer",
        "EmptyPreview",
        "ReactMarkdown",
        "h1",
        "h2",
        "h3",
        "p",
        "li",
        "code",
        "pre",
        "input"
      ],
      "children": []
    },
    {
      "name": "index",
      "path": "common/MarkdownEditor/index",
      "renders": [],
      "children": []
    },
    {
      "name": "MarkdownToolbar",
      "path": "common/MarkdownToolbar/MarkdownToolbar",
      "renders": [
        "div",
        "button"
      ],
      "children": []
    },
    {
      "name": "index",
      "path": "common/MarkdownToolbar/index",
      "renders": [],
      "children": []
    },
    {
      "name": "Modal",
      "path": "common/Modal/Modal",
      "renders": [],
      "children": []
    },
    {
      "name": "Panel",
      "path": "common/Panel/Panel",
      "renders": [
        "PanelWrapper",
        "PanelContainer",
        "PanelHeader",
        "HeaderContent",
        "PanelBadge",
        "ToggleButton",
        "MarkdownToolbar",
        "PanelContent",
        "PanelProvider",
        "PanelInner"
      ],
      "children": [
        "MarkdownToolbar"
      ]
    },
    {
      "name": "PanelContext",
      "path": "common/Panel/PanelContext",
      "renders": [
        "PanelContext.Provider"
      ],
      "children": []
    },
    {
      "name": "index",
      "path": "common/Panel/index",
      "renders": [],
      "children": []
    },
    {
      "name": "PanelTitle",
      "path": "common/Typography/PanelTitle",
      "renders": [],
      "children": []
    },
    {
      "name": "Typography",
      "path": "common/Typography/Typography",
      "renders": [],
      "children": []
    },
    {
      "name": "index",
      "path": "common/Typography/index",
      "renders": [],
      "children": []
    },
    {
      "name": "ComponentCatalog",
      "path": "dev/ComponentCatalog/ComponentCatalog",
      "renders": [
        "CatalogContainer",
        "EmptyState",
        "Sidebar",
        "div",
        "h2",
        "h3",
        "button",
        "span",
        "CategorySection",
        "ComponentItem",
        "MainArea",
        "TabBar",
        "Tab",
        "PreviewArea",
        "Suspense",
        "ControlPanel",
        "label",
        "input",
        "select",
        "option",
        "CodeView",
        "pre",
        "code",
        "p"
      ],
      "children": []
    },
    {
      "name": "RoomNote",
      "path": "dev/RoomNote/RoomNote",
      "renders": [
        "NoteContainer",
        "NoteHeader",
        "RoomTitle",
        "NoteContent",
        "MarkdownEditor"
      ],
      "children": [
        "MarkdownEditor"
      ]
    },
    {
      "name": "index",
      "path": "dev/RoomNote/index",
      "renders": [],
      "children": []
    },
    {
      "name": "SystemOverview",
      "path": "dev/SystemOverview/SystemOverview",
      "renders": [
        "g",
        "circle",
        "text",
        "line",
        "TreeNode",
        "OverviewContainer",
        "h1",
        "div",
        "p",
        "code",
        "GraphArea",
        "svg",
        "defs",
        "pattern",
        "path",
        "rect",
        "g",
        "TreeNode",
        "InfoPanel",
        "h3",
        "strong",
        "Legend",
        "LegendItem",
        "span"
      ],
      "children": []
    },
    {
      "name": "BaseRoom",
      "path": "layout/BaseRoom/BaseRoom",
      "renders": [
        "BaseRoomContainer",
        "RoomNote"
      ],
      "children": [
        "RoomNote"
      ]
    },
    {
      "name": "index",
      "path": "layout/BaseRoom/index",
      "renders": [],
      "children": []
    },
    {
      "name": "PanelGrid",
      "path": "layout/PanelGrid/PanelGrid",
      "renders": [
        "GridContainer"
      ],
      "children": []
    },
    {
      "name": "index",
      "path": "layout/PanelGrid/index",
      "renders": [],
      "children": []
    },
    {
      "name": "RoomCanvas",
      "path": "layout/RoomCanvas/RoomCanvas",
      "renders": [
        "CanvasContainer",
        "RoomsGrid",
        "RoomSlot",
        "DefaultRoomRenderer",
        "AtelierRoom",
        "BibliothequeRoom",
        "BoutiqueRoom",
        "CaveRoom",
        "ChambreRoom",
        "ComptoirRoom",
        "CuisineRoom",
        "ForgeRoom",
        "JardinRoom",
        "LaboratoireRoom",
        "SanctuaireRoom",
        "ScriptoriumRoom",
        "NavigationArrows"
      ],
      "children": [
        "AtelierRoom",
        "BibliothequeRoom",
        "BoutiqueRoom",
        "CaveRoom",
        "ChambreRoom",
        "ComptoirRoom",
        "CuisineRoom",
        "ForgeRoom",
        "JardinRoom",
        "LaboratoireRoom",
        "SanctuaireRoom",
        "ScriptoriumRoom",
        "NavigationArrows"
      ]
    },
    {
      "name": "SideTower",
      "path": "layout/SideTower/SideTower",
      "renders": [
        "TowerContainer",
        "TopTowerFloor",
        "ControlTower",
        "MiddleTowerFloor",
        "WorkbenchDrawer",
        "BottomTowerFloor",
        "SideTowerNotes"
      ],
      "children": [
        "ControlTower",
        "WorkbenchDrawer",
        "SideTowerNotes"
      ]
    },
    {
      "name": "StudioHall",
      "path": "layout/StudioHall/StudioHall",
      "renders": [
        "StudioContainer",
        "RoomCanvas",
        "SideTower"
      ],
      "children": [
        "RoomCanvas",
        "SideTower"
      ]
    },
    {
      "name": "ModalManager",
      "path": "modals/ModalManager",
      "renders": [
        "HealingPotionModal",
        "SleepPotionModal",
        "StrengthPotionModal",
        "SyncModal",
        "SettingsModal"
      ],
      "children": [
        "HealingPotionModal",
        "SleepPotionModal",
        "StrengthPotionModal",
        "SyncModal",
        "SettingsModal"
      ]
    },
    {
      "name": "HealingPotionModal",
      "path": "modals/PotionModals/HealingPotionModal",
      "renders": [
        "Modal",
        "TestContent",
        "h3",
        "div"
      ],
      "children": [
        "Modal"
      ]
    },
    {
      "name": "SleepPotionModal",
      "path": "modals/PotionModals/SleepPotionModal",
      "renders": [
        "Modal",
        "TestContent",
        "h3",
        "div"
      ],
      "children": [
        "Modal"
      ]
    },
    {
      "name": "StrengthPotionModal",
      "path": "modals/PotionModals/StrengthPotionModal",
      "renders": [
        "Modal",
        "TestContent",
        "h3",
        "div"
      ],
      "children": [
        "Modal"
      ]
    },
    {
      "name": "index",
      "path": "modals/PotionModals/index",
      "renders": [],
      "children": []
    },
    {
      "name": "SettingsModal",
      "path": "modals/SettingsModal/SettingsModal",
      "renders": [
        "Modal",
        "SettingsContainer",
        "SettingsSection",
        "SettingsTitle",
        "SettingsDescription",
        "InputGroup",
        "Label",
        "Select",
        "option",
        "SaveButton",
        "StatusMessage"
      ],
      "children": [
        "Modal"
      ]
    },
    {
      "name": "SyncModal",
      "path": "modals/SyncModal/SyncModal",
      "renders": [
        "Modal",
        "SyncContainer",
        "SyncSection",
        "SyncTitle",
        "SyncDescription",
        "InputGroup",
        "Label",
        "Input",
        "PasswordInput",
        "ActionButton",
        "ButtonGroup",
        "StatusMessage",
        "ConfigInfo",
        "ConfigRow"
      ],
      "children": [
        "Modal"
      ]
    },
    {
      "name": "ArrowButton",
      "path": "navigation/NavigationArrows/ArrowButton",
      "renders": [
        "ArrowContainer",
        "img"
      ],
      "children": []
    },
    {
      "name": "NavigationArrows",
      "path": "navigation/NavigationArrows/NavigationArrows",
      "renders": [
        "ArrowsContainer",
        "ArrowButton"
      ],
      "children": [
        "ArrowButton"
      ]
    },
    {
      "name": "index",
      "path": "navigation/NavigationArrows/index",
      "renders": [],
      "children": []
    },
    {
      "name": "AtelierRoom",
      "path": "rooms/Atelier/AtelierRoom",
      "renders": [
        "BaseRoom",
        "PanelGrid",
        "Panel",
        "MarkdownEditor"
      ],
      "children": [
        "BaseRoom",
        "PanelGrid",
        "Panel",
        "MarkdownEditor"
      ]
    },
    {
      "name": "BibliothequeRoom",
      "path": "rooms/Bibliotheque/BibliothequeRoom",
      "renders": [
        "BaseRoom",
        "BibliothequeGrid"
      ],
      "children": [
        "BaseRoom"
      ]
    },
    {
      "name": "index",
      "path": "rooms/Bibliotheque/index",
      "renders": [],
      "children": []
    },
    {
      "name": "BoutiqueRoom",
      "path": "rooms/Boutique/BoutiqueRoom",
      "renders": [
        "BaseRoom",
        "BoutiqueGrid"
      ],
      "children": [
        "BaseRoom"
      ]
    },
    {
      "name": "index",
      "path": "rooms/Boutique/index",
      "renders": [],
      "children": []
    },
    {
      "name": "CaveRoom",
      "path": "rooms/Cave/CaveRoom",
      "renders": [
        "BaseRoom",
        "CaveGrid"
      ],
      "children": [
        "BaseRoom"
      ]
    },
    {
      "name": "index",
      "path": "rooms/Cave/index",
      "renders": [],
      "children": []
    },
    {
      "name": "ChambreRoom",
      "path": "rooms/Chambre/ChambreRoom",
      "renders": [
        "BaseRoom",
        "ChambreTitle",
        "PanelGrid",
        "Panel",
        "div",
        "p",
        "small",
        "MarkdownEditor"
      ],
      "children": [
        "BaseRoom",
        "PanelGrid",
        "Panel",
        "MarkdownEditor"
      ]
    },
    {
      "name": "index",
      "path": "rooms/Chambre/index",
      "renders": [],
      "children": []
    },
    {
      "name": "ComptoirRoom",
      "path": "rooms/Comptoir/ComptoirRoom",
      "renders": [
        "BaseRoom",
        "ComptoirGrid"
      ],
      "children": [
        "BaseRoom"
      ]
    },
    {
      "name": "index",
      "path": "rooms/Comptoir/index",
      "renders": [],
      "children": []
    },
    {
      "name": "CuisineRoom",
      "path": "rooms/Cuisine/CuisineRoom",
      "renders": [
        "BaseRoom",
        "CuisineGrid"
      ],
      "children": [
        "BaseRoom"
      ]
    },
    {
      "name": "ForgeRoom",
      "path": "rooms/Forge/ForgeRoom",
      "renders": [
        "BaseRoom",
        "PanelGrid",
        "Panel",
        "ComponentCatalog",
        "SystemOverview",
        "ForgeToolbar",
        "Button"
      ],
      "children": [
        "BaseRoom",
        "PanelGrid",
        "Panel",
        "ComponentCatalog",
        "SystemOverview",
        "Button"
      ]
    },
    {
      "name": "index",
      "path": "rooms/Forge/index",
      "renders": [],
      "children": []
    },
    {
      "name": "JardinRoom",
      "path": "rooms/Jardin/JardinRoom",
      "renders": [
        "BaseRoom",
        "JardinGrid"
      ],
      "children": [
        "BaseRoom"
      ]
    },
    {
      "name": "LaboratoireRoom",
      "path": "rooms/Laboratoire/LaboratoireRoom",
      "renders": [
        "BaseRoom",
        "ControlHeader",
        "LaboTitle",
        "Button",
        "PanelGrid",
        "Panel",
        "WelcomeContent",
        "WelcomeEmoji",
        "WelcomeTitle",
        "WelcomeDescription",
        "WelcomeHint",
        "NoPanelContent",
        "NoPanelCenter",
        "LargeEmoji",
        "NoPanelSubtitle"
      ],
      "children": [
        "BaseRoom",
        "Button",
        "PanelGrid",
        "Panel"
      ]
    },
    {
      "name": "SanctuaireRoom",
      "path": "rooms/Sanctuaire/SanctuaireRoom",
      "renders": [
        "BaseRoom",
        "SanctuaireWrapper",
        "SanctuaireGrid"
      ],
      "children": [
        "BaseRoom"
      ]
    },
    {
      "name": "ScriptoriumRoom",
      "path": "rooms/Scriptorium/ScriptoriumRoom",
      "renders": [
        "BaseRoom",
        "ScriptoriumGrid"
      ],
      "children": [
        "BaseRoom"
      ]
    },
    {
      "name": "index",
      "path": "rooms/Scriptorium/index",
      "renders": [],
      "children": []
    },
    {
      "name": "ControlTower",
      "path": "tower/ControlTower/ControlTower",
      "renders": [
        "TowerContainer",
        "TopRow",
        "IconButton",
        "CenterRect",
        "div",
        "BottomRow"
      ],
      "children": [
        "IconButton"
      ]
    },
    {
      "name": "SideTowerNotes",
      "path": "tower/SideTowerNotes/SideTowerNotes",
      "renders": [
        "NoteContainer",
        "div",
        "span",
        "MarkdownToolbar",
        "MarkdownEditor"
      ],
      "children": [
        "MarkdownToolbar",
        "MarkdownEditor"
      ]
    },
    {
      "name": "WorkbenchDrawer",
      "path": "tower/WorkbenchDrawer/WorkbenchDrawer",
      "renders": [
        "DrawerContainer",
        "TabsHeader",
        "TabButton",
        "span",
        "TabContent",
        "ItemsGrid",
        "div",
        "IconButton"
      ],
      "children": [
        "IconButton"
      ]
    },
    {
      "name": "index",
      "path": "tower/index",
      "renders": [],
      "children": []
    },
    {
      "name": "ActionList",
      "path": "widgets/ActionList/ActionList",
      "renders": [
        "div",
        "input"
      ],
      "children": []
    },
    {
      "name": "ImageCarousel",
      "path": "widgets/ImageCarousel/ImageCarousel",
      "renders": [
        "div",
        "p",
        "input",
        "img",
        "button"
      ],
      "children": []
    },
    {
      "name": "MindLog",
      "path": "widgets/MindLog/MindLog",
      "renders": [
        "div",
        "select",
        "option",
        "br",
        "textarea"
      ],
      "children": []
    }
  ]
}